README.md
setup.py
blickfeld_scanner/__init__.py
blickfeld_scanner/discover.py
blickfeld_scanner/scanner.py
blickfeld_scanner/version.py
blickfeld_scanner.egg-info/PKG-INFO
blickfeld_scanner.egg-info/SOURCES.txt
blickfeld_scanner.egg-info/dependency_links.txt
blickfeld_scanner.egg-info/requires.txt
blickfeld_scanner.egg-info/top_level.txt
blickfeld_scanner/protocol/__init__.py
blickfeld_scanner/protocol/common_pb2.py
blickfeld_scanner/protocol/connection_pb2.py
blickfeld_scanner/protocol/error_pb2.py
blickfeld_scanner/protocol/options_pb2.py
blickfeld_scanner/protocol/config/__init__.py
blickfeld_scanner/protocol/config/advanced_pb2.py
blickfeld_scanner/protocol/config/algorithm_pb2.py
blickfeld_scanner/protocol/config/generate_pb2.py
blickfeld_scanner/protocol/config/named_scan_pattern_pb2.py
blickfeld_scanner/protocol/config/product_pb2.py
blickfeld_scanner/protocol/config/scan_pattern_pb2.py
blickfeld_scanner/protocol/config/secure_pb2.py
blickfeld_scanner/protocol/data/__init__.py
blickfeld_scanner/protocol/data/algorithm_pb2.py
blickfeld_scanner/protocol/data/frame_pb2.py
blickfeld_scanner/protocol/data/imu_pb2.py
blickfeld_scanner/protocol/data/point_cloud_pb2.py
blickfeld_scanner/protocol/data/point_pb2.py
blickfeld_scanner/protocol/data/scanline_pb2.py
blickfeld_scanner/protocol/file/__init__.py
blickfeld_scanner/protocol/file/general_pb2.py
blickfeld_scanner/protocol/file/point_cloud_pb2.py
blickfeld_scanner/protocol/status/__init__.py
blickfeld_scanner/protocol/status/imu_pb2.py
blickfeld_scanner/protocol/status/main_pb2.py
blickfeld_scanner/protocol/status/scanner_pb2.py
blickfeld_scanner/protocol/status/server_pb2.py
blickfeld_scanner/protocol/status/temperature_pb2.py
blickfeld_scanner/protocol/status/time_synchronization_pb2.py
blickfeld_scanner/protocol/stream/__init__.py
blickfeld_scanner/protocol/stream/connection_pb2.py
blickfeld_scanner/protocol/stream/event_pb2.py
blickfeld_scanner/protocol/update/__init__.py
blickfeld_scanner/protocol/update/hardware_pb2.py
blickfeld_scanner/protocol/update/manifest_pb2.py
blickfeld_scanner/stream/__init__.py
blickfeld_scanner/stream/imu.py
blickfeld_scanner/stream/point_cloud.py
blickfeld_scanner/stream/raw.py
