Metadata-Version: 2.1
Name: blickfeld-scanner
Version: 2.18.2
Summary: Python package to communicate with LiDAR devices of the Blickfeld GmbH.
Home-page: https://github.com/Blickfeld/blickfeld-scanner-lib
Author: Blickfeld GmbH
Author-email: opensource@blickfeld.com
License: UNKNOWN
Platform: UNKNOWN
Classifier: Programming Language :: Python :: 2
Classifier: Programming Language :: Python :: 3
Classifier: License :: OSI Approved :: BSD License
Classifier: Operating System :: OS Independent
Classifier: Topic :: Scientific/Engineering
Classifier: Topic :: Utilities
